django_infinite_icons-0.1.dist-info/DESCRIPTION.rst
django_infinite_icons-0.1.dist-info/METADATA
django_infinite_icons-0.1.dist-info/RECORD
django_infinite_icons-0.1.dist-info/WHEEL
django_infinite_icons-0.1.dist-info/metadata.json
django_infinite_icons-0.1.dist-info/top_level.txt
infinite_icons/__init__.py
infinite_icons/svg_data.py
infinite_icons/tests.py
infinite_icons/static/feather/activity.svg
infinite_icons/static/feather/airplay.svg
infinite_icons/static/feather/alert-circle.svg
infinite_icons/static/feather/alert-octagon.svg
infinite_icons/static/feather/alert-triangle.svg
infinite_icons/static/feather/align-center.svg
infinite_icons/static/feather/align-justify.svg
infinite_icons/static/feather/align-left.svg
infinite_icons/static/feather/align-right.svg
infinite_icons/static/feather/anchor.svg
infinite_icons/static/feather/aperture.svg
infinite_icons/static/feather/archive.svg
infinite_icons/static/feather/arrow-down-circle.svg
infinite_icons/static/feather/arrow-down-left.svg
infinite_icons/static/feather/arrow-down-right.svg
infinite_icons/static/feather/arrow-down.svg
infinite_icons/static/feather/arrow-left-circle.svg
infinite_icons/static/feather/arrow-left.svg
infinite_icons/static/feather/arrow-right-circle.svg
infinite_icons/static/feather/arrow-right.svg
infinite_icons/static/feather/arrow-up-circle.svg
infinite_icons/static/feather/arrow-up-left.svg
infinite_icons/static/feather/arrow-up-right.svg
infinite_icons/static/feather/arrow-up.svg
infinite_icons/static/feather/at-sign.svg
infinite_icons/static/feather/award.svg
infinite_icons/static/feather/bar-chart-2.svg
infinite_icons/static/feather/bar-chart.svg
infinite_icons/static/feather/battery-charging.svg
infinite_icons/static/feather/battery.svg
infinite_icons/static/feather/bell-off.svg
infinite_icons/static/feather/bell.svg
infinite_icons/static/feather/bluetooth.svg
infinite_icons/static/feather/bold.svg
infinite_icons/static/feather/book-open.svg
infinite_icons/static/feather/book.svg
infinite_icons/static/feather/bookmark.svg
infinite_icons/static/feather/box.svg
infinite_icons/static/feather/briefcase.svg
infinite_icons/static/feather/calendar.svg
infinite_icons/static/feather/camera-off.svg
