Metadata-Version: 2.0
Name: django-infinite-icons
Version: 0.1
Summary: Django-infinite-icons will help you to render SVG icons.
Home-page: https://github.com/akashdk/django-infinite-icons
Author: Akash Dhinagaran
Author-email: imakkash@gmail.com
License: MIT License
Project-URL: Documentation, https://github.com/akashdk/django-infinite-icons/blob/master/README.md
Project-URL: Say Thanks!, https://akkash.me
Project-URL: Source, https://github.com/akashdk/django-infinite-icons
Project-URL: Tracker, https://github.com/akashdk/django-infinite-icons/issues
Platform: UNKNOWN
Classifier: Development Status :: 4 - Beta
Classifier: Environment :: Web Environment
Classifier: Framework :: Django
Classifier: Intended Audience :: Developers
Classifier: License :: OSI Approved :: MIT License
Classifier: Operating System :: OS Independent
Classifier: Programming Language :: Python
Classifier: Programming Language :: Python :: 2.7
Classifier: Programming Language :: Python :: 3
Classifier: Programming Language :: Python :: 3.4
Classifier: Programming Language :: Python :: 3.5
Classifier: Programming Language :: Python :: 3.6
Classifier: Programming Language :: Python :: 3.7
Classifier: Topic :: Software Development :: Libraries :: Python Modules
Requires: django (>= 1.11)
